README.md
setup.py
lnpbp_testkit/__init__.py
lnpbp_testkit/cadr.py
lnpbp_testkit/lightning.py
lnpbp_testkit/lnd.py
lnpbp_testkit/network.py
lnpbp_testkit/parsing.py
lnpbp_testkit.egg-info/PKG-INFO
lnpbp_testkit.egg-info/SOURCES.txt
lnpbp_testkit.egg-info/dependency_links.txt
lnpbp_testkit.egg-info/not-zip-safe
lnpbp_testkit.egg-info/requires.txt
lnpbp_testkit.egg-info/top_level.txt