Metadata-Version: 2.1
Name: lnpbp-testkit
Version: 0.1.1
Summary: A framework for writing automated tests of applications using LNP/BP
Home-page: https://github.com/Kixunil/lnpbp-testkit
Author: Martin Habovstiak
Author-email: martin.habovstiak@gmail.com
License: MIT
Keywords: bitcoin lightning-network tests
Platform: UNKNOWN
Classifier: Development Status :: 4 - Beta
Classifier: Intended Audience :: Developers
Classifier: License :: OSI Approved :: MIT License
Classifier: Operating System :: POSIX :: Linux
Classifier: Programming Language :: Python
Classifier: Programming Language :: Python :: 3
Classifier: Programming Language :: Python :: 3.7
Classifier: Programming Language :: Python :: 3.8
Classifier: Topic :: Software Development :: Testing
Requires-Python: >=3.7.3
